{
    "root": "/projects/xingchen/Matsuura/DG/script",
    "program": "../main/main.py",
    "codePath": "../main/main.py",
    "startedAt": "2020-05-19T04:12:49.523271",
    "host": "vamp-1",
    "username": "xiz168",
    "executable": "/afs/cs.pitt.edu/usr0/xiz168/miniconda3/envs/pytorch1_0/bin/python",
    "os": "Linux-4.15.0-88-generic-x86_64-with-debian-buster-sid",
    "python": "3.6.10",
    "gpu": "GeForce RTX 2080 Ti",
    "gpu_count": 4,
    "cpu_count": 40,
    "cuda": "10.0.130",
    "args": [
        "--data-root=../data/pacs/kfold/",
        "--save-root=../data/result/deep_all_only_color_jitter",
        "--result-dir=PACS/default/cartoon4",
        "--train=deepall",
        "--data=PACS",
        "--model=caffenet",
        "--exp-num=2",
        "--gpu=0",
        "--num-epoch=30",
        "--scheduler=step",
        "--lr=1e-3",
        "--lr-step=24",
        "--lr-decay-gamma=0.1",
        "--nesterov",
        "--fc-weight=10.0",
        "--color-jitter",
        "--only-color-jitter",
        "--min-scale=0.8",
        "--wandb-proj-name=Mat_Deepall_Aug_onlyColorJitter",
        "--wandb-run-name=a_run4"
    ],
    "state": "finished",
    "jobType": null,
    "mode": "run",
    "name": "a_run4",
    "project": "Mat_Deepall_Aug_onlyColorJitter",
    "heartbeatAt": "2020-05-19T04:21:10.725064",
    "exitcode": 0
}
